README.md
setup.py
blip_session/__init__.py
blip_session/blip_session.py
blip_session.egg-info/PKG-INFO
blip_session.egg-info/SOURCES.txt
blip_session.egg-info/dependency_links.txt
blip_session.egg-info/requires.txt
blip_session.egg-info/top_level.txt