Metadata-Version: 1.1
Name: blip-session
Version: 0.0.1
Summary: Provide a session class from requests module to use as a BLiP Session.
Home-page: https://github.com/chr0m1ng/blip-session
Author: Gabriel Rodrigues dos Santos
Author-email: gabrielr@take.net
License: MIT
Download-URL: https://github.com/chr0m1ng/blip-session/archive/v0.0.1.tar.gz
Keywords: lime,blip,chatbot
Platform: UNKNOWN
Classifier: Development Status :: 4 - Beta
Classifier: Intended Audience :: Developers
Classifier: Topic :: Software Development :: Build Tools
Classifier: License :: OSI Approved :: MIT License
Classifier: Programming Language :: Python :: 3.5
Classifier: Programming Language :: Python :: 3.6
Classifier: Programming Language :: Python :: 3.7
